README.md
_mutableint.c
setup.py
mutableint/__init__.py
mutableint.egg-info/PKG-INFO
mutableint.egg-info/SOURCES.txt
mutableint.egg-info/dependency_links.txt
mutableint.egg-info/requires.txt
mutableint.egg-info/top_level.txt