Metadata-Version: 2.1
Name: mutableint
Version: 0.1
Summary: Mutable Integer package, a subclass of int
Home-page: https://github.com/hevangel/mutable_int
Author: Horace Chan
Author-email: git@horace.org
License: UNKNOWN
Platform: UNKNOWN
Classifier: Programming Language :: Python :: 3
Classifier: License :: OSI Approved :: MIT License
Classifier: Operating System :: OS Independent
Requires-Python: >=3.5
